invoice_generate/__init__.py
invoice_generate/templates/template.tpl
invoice_generate-0.1.3.dist-info/entry_points.txt
invoice_generate-0.1.3.dist-info/WHEEL
invoice_generate-0.1.3.dist-info/METADATA
invoice_generate-0.1.3.dist-info/RECORD
