Metadata-Version: 2.1
Name: invoice-generate
Version: 0.1.3
Summary: 
Author: Eric Prykhodko
Author-email: eprykhodko@bcdtriptech.com
Requires-Python: >=3.6,<4.0
Classifier: Programming Language :: Python :: 3
Classifier: Programming Language :: Python :: 3.6
Classifier: Programming Language :: Python :: 3.7
Classifier: Programming Language :: Python :: 3.8
Requires-Dist: click (>=7.0,<8.0)
Requires-Dist: jinja2 (>=2.10.3,<3.0.0)
Requires-Dist: pdfkit (>=0.6.1,<0.7.0)
Requires-Dist: python-dateutil (>=2.8.1,<3.0.0)
Requires-Dist: toml (>=0.10.0,<0.11.0)
